DetectAssetPurpose/__init__.py
DetectAssetPurpose/config.yaml
DetectAssetPurpose/detect_image.py
DetectAssetPurpose/detect_video.py
DetectAssetPurpose/mapping.py
DetectAssetPurpose/run_detection.py
detectassetpurpose-0.1.11.dist-info/LICENSE
detectassetpurpose-0.1.11.dist-info/METADATA
detectassetpurpose-0.1.11.dist-info/WHEEL
detectassetpurpose-0.1.11.dist-info/top_level.txt
detectassetpurpose-0.1.11.dist-info/RECORD
