Metadata-Version: 2.2
Name: DetectAssetPurpose
Version: 0.1.11
Summary: Package provides detection of asset purpose using LLM identification: Brand Building or Conversion
Author: Irina White
Author-email: i.white@neuronsinc.com
License: MIT
License-File: LICENSE
Dynamic: author
Dynamic: author-email
Dynamic: license
Dynamic: summary
